{
  "id": "13103",
  "name": "Gumball Swing Out",
  "image": "https://img.gamemonetize.com/es1gzxzgbul2hy9w2d468rewxoslng11/512x384.jpg",
  "gameUrl": "https://html5.gamemonetize.com/es1gzxzgbul2hy9w2d468rewxoslng11/",
  "description": "In the crazy world of Gumball everything is possible, like having to swing in an empty space to jump from mound to mound, trying to make the jumper land just above the flag, and take into account its weight and other characteristics such as wind and mood of the beans.",
  "categoryId": 5,
  "instructions": "Simple gameplay with efficient and easy to learn controls ",
  "tags": "Boys, Cartoon, Cartoon Network, Girls, Kids, Stickman, Sword"
}
