{
  "id": "23981",
  "name": "Extreme Jelly Shift 3D Game",
  "image": "https://img.gamemonetize.com/8v7ijxx38ysk36xszqghgk4uml6law2e/512x384.jpg",
  "gameUrl": "https://html5.gamemonetize.com/8v7ijxx38ysk36xszqghgk4uml6law2e/",
  "description": "Extreme Jelly Shift 3D is a fun casual game. Do you like jelly? The soft jelly can change its shape. In this game, you can control the changeable jelly on an obstacle course! Protect your jelly from being crashed and reach the finish line! Have fun!",
  "categoryId": 2,
  "instructions": "Tap or click ",
  "tags": "3D, 3D Games, Fun, Funny, H5, HTML5, Kid, Kids"
}
