{
  "id": "25075",
  "name": "Rope Dude Game",
  "image": "https://img.gamemonetize.com/5wz4kbn1cuwq4jztgsfzjus9o3esd0g7/512x384.jpg",
  "gameUrl": "https://html5.gamemonetize.com/5wz4kbn1cuwq4jztgsfzjus9o3esd0g7/",
  "description": "Rope Dude is a free puzzle and casual online game for boys to enjoy! Just cut the ropes to kill the mannequin dude through various props, such as lasers, arrows, spinning spiked discs, and so on. The game has exquisite, smooth, and enjoyable gameplay, come to unlock more levels as you can. Mobile, Tablet, and Desktop are playable. Release your stress and have fun!",
  "categoryId": 2,
  "instructions": "Mouse or tap to play ",
  "tags": "3D, Android, Boy, Fun, HTML5, Kids, Online, Puzzle, Skill"
}
