{
  "id": "25111",
  "name": "Prison Gates",
  "image": "https://img.gamemonetize.com/sl4b1jft5toksui8ogwb80a76xofkevt/512x384.jpg",
  "gameUrl": "https://html5.gamemonetize.com/sl4b1jft5toksui8ogwb80a76xofkevt/",
  "description": "Prison Gates is a stickman running game where you try to pass through gates while avoiding criminals. Your mission in this game; is to pass through the right one of the 2 gates that will appear in front of you while running. One of these passages will be open and the other will be closed. If you try to pass through the closed gate, the criminals will catch you and the game will be over. When you pass through the right gate, the criminals chasing after you will not catch you and you will succeed.",
  "categoryId": 5,
  "instructions": "PC MOVE LEFT-RIGHT ARROW KEYS MOBILE MOVE LEFT-RIGHT SWIPE FINGER",
  "tags": "Avoid, Best, Casual, Escape, Hot, Hypercasual, Mobile, Obstacle, Platform, Rescue, run, running, Stickman"
}
