{
  "id": "26458",
  "name": "Pizza Delivery Run",
  "image": "https://img.gamemonetize.com/qn3v9rfw4o45io2f3li1lgrzudco3de9/512x384.jpg",
  "gameUrl": "https://html5.gamemonetize.com/qn3v9rfw4o45io2f3li1lgrzudco3de9/",
  "description": "Pizza Delivery Run is a fun and free online running game for boys played on Puzzlegame. You need to keep collecting pizzas and delivering them to your destination. Too many obstacles will cause you to fail, so you must be careful and deliver pizzas safely. When you get to the finish line, the more pizzas, the higher the score. Play on Mobile, Tablet, or Desktop.",
  "categoryId": 2,
  "instructions": "Mouse or tap to play",
  "tags": "3D, Android, Avoid, Boy, Brain, Fun, HTML5, Kids, Number, Obstacle, Online, Puzzle, running, Skill"
}
