{
  "id": "28822",
  "name": "Star of warfare ",
  "image": "https://img.gamemonetize.com/i1rug1a2wfumsk5a72vqmt7zry8ddjn4/512x384.jpg",
  "gameUrl": "https://html5.gamemonetize.com/i1rug1a2wfumsk5a72vqmt7zry8ddjn4/",
  "description": "Star of warfare is a free multiplayer first-person shooter game that currently has 3 game modes deathmatch, team deathmatch an like capture the flag but will be updated with more modes battle royal and gun game. There are three weapon classes available in Star of warfare. You can use an assault rifle sniper or shotgun with more weapons being added soon.",
  "categoryId": 4,
  "instructions": "WASD to move Space to jump left mouse button to shoot right mouse button to aim Shift to run P to pause the game Enter to respawn F to pick up a gun R to reload your weapon C to crouch 1 2 3 to change your",
  "tags": "Action, Army, Multiplayer, weapons, WebGL"
}
