{
  "id": "29354",
  "name": "Real Airplane Simulator",
  "image": "https://img.gamemonetize.com/l2mrm0gwkvuj1g0qy0acw6fj7xnzxmas/512x384.jpg",
  "gameUrl": "https://html5.gamemonetize.com/l2mrm0gwkvuj1g0qy0acw6fj7xnzxmas/",
  "description": "Here is an airplane-driving simulation game. There are many different airplanes to unlock and select in the garage. Following the green arrow and lines, adjust the height instantly. More practice will help you complete all levels.",
  "categoryId": 1,
  "instructions": "Switch views for better driving sense Follow the hints",
  "tags": "3D, airplane, Driving, Mobile, Parking, Simulation, Timing"
}
