{
  "id": "30154",
  "name": "Stickman Merge Battle: Arena",
  "image": "https://img.gamemonetize.com/obyhafhugknxn37yy4vsed6yknb9d6rl/512x384.jpg",
  "gameUrl": "https://html5.gamemonetize.com/obyhafhugknxn37yy4vsed6yknb9d6rl/",
  "description": "An exciting strategic merge game where you have to demonstrate your advantage over the red stickman invaders. Create your army of stickmen, show your wit in the formation of troops and defeat all bosses. Less than 1% percent of players are able to unlock all stickmen and complete the game. - 3D stickmen - Each level is harder than the previous one - Intuitive controls - Boss difficulty every ten levels - Tactical game for all ages",
  "categoryId": 5,
  "instructions": "- Click Sword and arrow button to purchase units - Click Tile button to purchase tiles - Drag units between tiles to improve your strategic positioning - Merge two units of the same type to get the next tier unit",
  "tags": "1 Player, 3D, Action, Arena, Army, Battle, Bow, Clash, Enemy, Fight, Hypercasual, Management, Stickman, Strategy"
}
