{
  "id": "30394",
  "name": "Telekinesis Attack",
  "image": "https://img.gamemonetize.com/mdwhevqlrf9seap60s9gr6bbl18njy4u/512x384.jpg",
  "gameUrl": "https://html5.gamemonetize.com/mdwhevqlrf9seap60s9gr6bbl18njy4u/",
  "description": "Use your telekinesis magic power! Gain the ability to control the power of thought! Throw your enemies wherever you want, hit them against whatever you want and deal with them however you want! Using your unique power, defeat all enemies, interact with different objects, take away weapons from enemies and be the strongest!",
  "categoryId": 4,
  "instructions": "Control by pulling enemies just hold down the mouse button on the enemy and pull him in different directions to defeat the enemy just throw him in any direction ",
  "tags": "3D Games, Fighting, First Person Shooter, Magic, Shoot, Shooter, Stickman, Superhero, Unity3D"
}
