{
  "id": "30574",
  "name": "Bubble Ocean",
  "image": "https://img.gamemonetize.com/c6ga66lnynydlu6ycjpl5bxlhjmhy9le/512x384.jpg",
  "gameUrl": "https://html5.gamemonetize.com/c6ga66lnynydlu6ycjpl5bxlhjmhy9le/",
  "description": "A tap game to pove your speed! You are in control of the ocean and you must create bubbles to bring the pollution back to where it came from! Show them what you are made of!",
  "categoryId": 4,
  "instructions": "Mouse click or tap to play",
  "tags": "Bubble, Clicker"
}
