{
  "id": "30906",
  "name": "2048 The King Return",
  "image": "https://img.gamemonetize.com/n0z7uvsy5ra3t46g0040weanftotqc8p/512x384.jpg",
  "gameUrl": "https://html5.gamemonetize.com/n0z7uvsy5ra3t46g0040weanftotqc8p/",
  "description": "In the game 2048: The Kings Return, players control the characters lateral movement, aiming to destroy barrels for weapon upgrades. Website Developer &lt;a href='https://www.bestcrazygames.com'&gt;https://www.bestcrazygames.com&lt;/a&gt;",
  "categoryId": 4,
  "instructions": "Mouse click or tap to play",
  "tags": "2048, HTML5, Mentolatux, Mobile, Shooting, unity, WebGL"
}
