{
  "id": "31136",
  "name": "World in Danger Earth Attack",
  "image": "https://img.gamemonetize.com/eiz7yg0j236g0v2bjldy88w41zdvfg0z/512x384.jpg",
  "gameUrl": "https://html5.gamemonetize.com/eiz7yg0j236g0v2bjldy88w41zdvfg0z/",
  "description": "The world is in danger and under attack! Evil planets invade the Solar System and want to destroy the Earth. But the Earth will attack! And the Earth will not be alone, the moon will be together in this battle. Help to rotate the Planet Earth to shoot the enemy planets and destroy them before they can destroy the Earth. There are many weapons, evolve, increase its speed, and survive to crash all planets!",
  "categoryId": 4,
  "instructions": "Move earth with arrow-keys to shoot the enemy planet ",
  "tags": "Air, Alien"
}
