{
  "id": "31801",
  "name": "Craft Theft War",
  "image": "https://img.gamemonetize.com/2w7rnj6q5cnt9jt81l0m7s27uqqyqq0f/512x384.jpg",
  "gameUrl": "https://html5.gamemonetize.com/2w7rnj6q5cnt9jt81l0m7s27uqqyqq0f/",
  "description": "Immerse yourself in the best open-world action-adventure sandbox game, Craft Theft War, inspired by pixel voxel cube craft style online shooting games. Enjoy a vast selection of action-packed games, cool games, and relaxing games, all within a sprawling sandbox environment. This game offers an unparalleled online gaming experience, combining the best elements of open-world adventure, sandbox gameplay, and multiplayer action. Join the fun today and discover why its one of the best online games!",
  "categoryId": 1,
  "instructions": "Move WASD Aim Mouse Shoot Left Click Jump Space Sprint Shift Reload R ",
  "tags": "Action, Battle, Bubble Shooter, Multiplayer, Shooting, War"
}
