{
  "id": "33266",
  "name": "Matrix Man",
  "image": "https://img.gamemonetize.com/4x2lh9xfsht8s81bh0fhut7987t49wbr/512x384.jpg",
  "gameUrl": "https://html5.gamemonetize.com/4x2lh9xfsht8s81bh0fhut7987t49wbr/",
  "description": "MATRIX MAN: OVERRIDE Escape the System, Become the Glitch! The world is a lie, a digital prison controlled by weak NPCs &amp;zwj;. You are built different&amp;mdash;Matrix Man&amp;mdash;a high-value shooter with insane reflexes, bullet-time dodges &amp;zwj;, and next-level hacking skills. RUN the system or RULE it. Headshots only&amp;mdash;no weak moves. Unlock forbidden cyber-weapons. Break free, take over, and OWN the game. Most will stay plugged in. Only legends will OVERRIDE. Are you ready?",
  "categoryId": 4,
  "instructions": "Move Arrow keys WASD Aim Mouse Jump Space J Fire Left Mouse Button Z Throw Disruptor Right Mouse Button X Slow-Mo Focus Left Shift C Cycle Weapons Mouse Wheel Q E Enter Vehicle E Enter Pause Esc P Mute Audio M Change View V",
  "tags": "First Person Shooter, fps, Impostor, IO, Killing, Shoot 'Em Up, Shooter, Shooting, Train"
}
