{
  "id": "22066",
  "name": "2048ラン3D",
  "image": "https://img.gamemonetize.com/z7os7btei3467tg9rfuzgkpl1pzegcv9/512x384.jpg",
  "gameUrl": "https://html5.gamemonetize.com/z7os7btei3467tg9rfuzgkpl1pzegcv9/",
  "description": "2048ラン3Dは、男の子向けの新しい無料デジタルオンラインゲームです。ゲームでは、自分のボールを操作して異なる数字と合体させましょう！同じ数字と色のボールを合体させて、2048まで合体させることができます。同時に、道路には多くの障害物があります。最終得点は合体させた数字によって決まります。数字が大きいほど、得点が高くなり、報酬も豊富になります。楽しんでください！",
  "categoryId": 2,
  "instructions": "マウスまたはタップでプレイ",
  "tags": "3D, Android, Arcade, Ball, Boy, Brain, Fun, HTML5, Kids, Math, Number, Obstacle, Online, Puzzle, running"
}
