{
  "id": "23404",
  "name": "ピンを動かせ2ゲーム",
  "image": "https://img.gamemonetize.com/hqx9ru2z0d90grbrp7e6ryi8qoajop8l/512x384.jpg",
  "gameUrl": "https://html5.gamemonetize.com/hqx9ru2z0d90grbrp7e6ryi8qoajop8l/",
  "description": "「ピンを動かせ2」は、男の子向けの無料で簡単なゲームですが、罠に注意が必要です。すべてのボールをカップに入れる必要があります。正しくピンを抜いて目標を達成する必要があります。一部のボールは無色で、カップに入る前に他の色のボールに触れて色をつける必要があります。ですから、ピンを抜く前によく考えましょう。各レベルはデザインを完成させますので、自分自身に挑戦してみてください！",
  "categoryId": 2,
  "instructions": "マウスまたはタップでプレイ",
  "tags": "3D, Android, 回避, ボール, 男の子, ブレイン, 楽しい, HTML5, 子供, 障害物, オンライン, パズル, スキル"
}
