{
  "id": "28583",
  "name": "フライデーナイトファンキンカラーブッキングブックオンライン",
  "image": "https://img.gamemonetize.com/64bnf024xxaisptve9v4au2sb4axg2ca/512x384.jpg",
  "gameUrl": "https://html5.gamemonetize.com/64bnf024xxaisptve9v4au2sb4axg2ca/",
  "description": "FNFカラーブッキングブック、またはフライデーナイトファンキンカラーブッキングブックは、プレイヤーにFriday Night Funkinのリズミカルな世界に没頭し、芸術的なスキルを表現する機会を提供するエキサイティングでクリエイティブなゲームです。人気のリズムゲームからインスピレーションを得たFNFカラーブッキングブックは、アイコンキャラクター、記憶に残るシーン、ゲームのビビッドな背景をフィーチャーした幅広いカラーブッキングページを提供します。",
  "categoryId": 2,
  "instructions": "マウスを使用してオンラインでFriday Night Funkinカラーブッキングブックをプレイ",
  "tags": "Coloring, Educational"
}
