{
  "id": "29391",
  "name": "ゾンビディフェンス：ウォーZサバイバル",
  "image": "https://img.gamemonetize.com/sj7s1t0c6x9u5k021ne0tp7wi3q90b5q/512x384.jpg",
  "gameUrl": "https://html5.gamemonetize.com/sj7s1t0c6x9u5k021ne0tp7wi3q90b5q/",
  "description": "ゾンビディフェンス：ウォーZサバイバル、究極のゾンビゲームがあなたのゲーム欲求を満たすために登場しました！大量の食肉ゾンビとの戦いに備え、迫り来るゾンビの津波から自分の命を必死に守りましょう。これらのアンデッドの数は圧倒的です。彼らの爪から逃れることは困難な任務かもしれませんが、恐れることはありません。これらの容赦ない存在との戦いはまだ始まったばかりです！強力な火器を装備し、熟練したゾンビ捕獲者としての役割が、この止められないゾンビの波を阻止する鍵となります。勇気を振り絞り、このスリリングな旅に出発しましょう！",
  "categoryId": 2,
  "instructions": "クリックしてプレイ",
  "tags": "Collecting, Defense, Fighting, Gun, War, weapons, Zombie"
}
