{
  "id": "29865",
  "name": "ギャングファイターズ",
  "image": "https://img.gamemonetize.com/dmjz4ty5drd9aww9yq588icmnenprlu6/512x384.jpg",
  "gameUrl": "https://html5.gamemonetize.com/dmjz4ty5drd9aww9yq588icmnenprlu6/",
  "description": "危険な街でギャングファイターズゲームと一緒に冒険に出かけてみませんか？箱を壊し、地面からアイテムを拾い、街の悪者たちと戦いましょう。街での戦いだけでなく、友達と一緒に冒険をすることも、2P対戦モードで友達と戦うこともできます。地面からコインを拾うのを忘れないでください。お金を使ってショップでキャラクターを強化できます。冒険を始めましょう！",
  "categoryId": 1,
  "instructions": "プレイヤー1：移動はW A S D、ジャンプはSPACE、パンチはF、拾いはPick Up、キックはG、防御はT。プレイヤー2：移動は矢印キー、ジャンプはP、パンチはK、拾いはL、キックはDefend O",
  "tags": "2 Player, 2 Player Games, 3D, アクション, アドベンチャー, ファイト, 格闘, 射撃, ストリートファイト, WebGL"
}
