{
  "id": "30639",
  "name": "スキビディトイレVSカメラマンスナイパー",
  "image": "https://img.gamemonetize.com/z92hff1p2awvhpj88z86fox8arex1a95/512x384.jpg",
  "gameUrl": "https://html5.gamemonetize.com/z92hff1p2awvhpj88z86fox8arex1a95/",
  "description": "カメラマンはトイレマンの赤信号青信号ゲームで生き残ろうとしています。トイレマンが赤信号と言った時に動いているカメラマンがいたら、スナイパーガンで彼を破壊しなければなりません。狙う時は、正しいプレイヤーを撃つように注意しなければなりません。正しいプレイヤーを撃てば、追加ポイントを獲得できます。友達と競争して最高得点を競いましょう。今すぐトイレVSカメラマンスナイパーをプレイしましょう！",
  "categoryId": 4,
  "instructions": "マウスのロック解除 Lでスナイパーを動かす マウスでズーム 右クリックで発砲 左クリックでズームの拡大縮小 マウスホイール",
  "tags": "3D, Action, Battle, Enemy, Gun, Prison, Shooting, Skibidi, Skibidi Toilet, Sniper, War, weapons, WebGL"
}
