{
  "id": "30885",
  "name": "モンスターDIY作成",
  "image": "https://img.gamemonetize.com/alp1qgvb8i09llmagl5qwyni66akh7ic/512x384.jpg",
  "gameUrl": "https://html5.gamemonetize.com/alp1qgvb8i09llmagl5qwyni66akh7ic/",
  "description": "「モンスターフェイスを選べ！」で自分だけの恐ろしい傑作を作りましょう！スキンクリエイターに没頭し、スキビディ、グリマシー、ポピープレイタイムなど、トレンドのモンスターからインスピレーションを得て、頭から足までユニークなクリーチャーを作り上げましょう。様々な要素を組み合わせて、自分のスタイルを反映した一風変わったクリーチャーをデザインしましょう。友達と自分の作品をシェアし、恐ろしい創造性を披露しましょう！さらに、このゲーム専用の特別なパーツを解除しましょう。ウェブサイト開発者 &lt;a href='https://www.bestcrazygames.com'&gt;https://www.bestcrazygames.com&lt;/a&gt;",
  "categoryId": 1,
  "instructions": "マウスクリックまたはタップでプレイ",
  "tags": "1人プレイ, 2D, Android, 着せ替え, HTML5, iPad, iPhone, Mentolatux, モバイル, モンスター"
}
