{
  "id": "31832",
  "name": "パガンズパッセージ",
  "image": "https://img.gamemonetize.com/gvo42hg07bi459z2zmeciw5d2khq2wrn/512x384.jpg",
  "gameUrl": "https://html5.gamemonetize.com/gvo42hg07bi459z2zmeciw5d2khq2wrn/",
  "description": "パガンズパッセージはアクションゲームで、ドルイドを率いて10の儀式を完了し、古の存在を目覚めさせるのがミッションです。敵を撃ってドルイドたちの目標を助け、様々なアーティファクトを集め、ランキングトップに登るチャレンジを試みましょう！",
  "categoryId": 4,
  "instructions": "数字1、2、3を使って、橋とスカルの色を緑、青、赤から選びます スペースキーを押して選択したスカルから撃ちます スワイプで沼地の任意の場所に選択した色のタイル橋を置きます 右クリックでタイルを取り除きます",
  "tags": "Arcade, Shooting, Strategy"
}
