{
  "id": "32509",
  "name": "消防車運転シミュレーター2024",
  "image": "https://img.gamemonetize.com/ndh1rwjfkejjktdkkwb2bl80tgpg5l03/512x384.jpg",
  "gameUrl": "https://html5.gamemonetize.com/ndh1rwjfkejjktdkkwb2bl80tgpg5l03/",
  "description": "消防車運転シミュレーター2024では、プレイヤーは英雄的な消防士の役割を担い、強力な消防車を運転して忙しい市街地、田舎道、険しい山道を進みます。目標は、緊急現場に迅速かつ効率的に到着し、障害物や交通をナビゲートしながらチームの安全を確保することです。プレイヤーは車両のコントロールをマスターし、サイレンを戦略的に使用して道を開け、プレッシャーの中でも冷静さを保つ必要があります。WASDで運転、ウェブ開発 &lt;a href=''&gt;&lt;/a&gt;",
  "categoryId": 1,
  "instructions": "WASDで運転",
  "tags": "火災, 消防士, メントラトゥックス, シミュレーター, トラック, トラックス, 車両"
}
