{
  "id": "9168",
  "name": "スティックマンVSスティックマン弾丸射撃",
  "image": "https://img.gamemonetize.com/2qt527t3xctpvcfv0yw2mzibgikhex5h/512x384.jpg",
  "gameUrl": "https://html5.gamemonetize.com/2qt527t3xctpvcfv0yw2mzibgikhex5h/",
  "description": "スプリームデュエリストスティックマンは、面白くて狂ったスティックマンモバイルゲームです。 - 多くのマップ（新しいマップエディター付き） - 簡単な操作 - プレイして新しいスキンを解除 - 1プレイヤー、2プレイヤー、サバイバルモード - リアルなスティックマンラグドール - 2D物理スティックファイトバトル - 自分だけのスティックマンウォリアーを作成 収集可能なモード： - 重力（ON/OFF） - インスタントKO（無効にすると、水や溶岩などが接触するとダメージを与える） - エネルギーシールド（無効にすると、スティックマンは曲がることができる） 2プレイヤーモードでキャラクターを選択して友達とプレイできます。RHGスティックファイトゲーム。",
  "categoryId": 5,
  "instructions": "",
  "tags": "ファイト, 銃, 殺害, シューティング, スティックマン"
}
