{
  "id": "9445",
  "name": "スティックマンバックフリップキラー",
  "image": "https://img.gamemonetize.com/98r95qx89742pharpw9k8iseywsnz439/512x384.jpg",
  "gameUrl": "https://html5.gamemonetize.com/98r95qx89742pharpw9k8iseywsnz439/",
  "description": "パルクールスキル、武器、エピックなスローモーション効果を使ってスティックマンを破壊します。服装とパルクールスキルをアップグレードし、武器を購入して、世界で最も優れたスティックマンになりましょう。クールなパルクールレベルをクリアし、キラーモードで敵を破壊してください。新しいステージシステムにより、新しいレベルがよりエキサイティングで面白くなります。",
  "categoryId": 5,
  "instructions": "注意深く探せば、自分を守るための武器が見つかるかもしれません。",
  "tags": "3D, 男の子, ファイト, 戦闘, 殺害, スティックマン"
}
